Verilog Files/carrySave.v
`timescale 1ns / 1ps
//////////////////////////////////////////////////////////////////////////////////
// Company: 
// Engineer: 
// 
// Create Date: 05/10/2025 06:09:13 PM
// Design Name: 
// Module Name: carrySave
// Project Name: 
// Target Devices: 
// Tool Versions: 
// Description: 
// 
// Dependencies: 
// 
// Revision:
// Revision 0.01 - File Created
// Additional Comments:
// 
//////////////////////////////////////////////////////////////////////////////////


module carrySave(input clk, rst, x , y , output reg sum);
wire HSUM1;
reg SC; 
assign HSUM1 = y ^ SC;
assign hco1 = y & SC;
wire hsum2, hco2;
assign hsum2 = x ^ HSUM1;
assign hco2 = x & HSUM1;

always @ (posedge clk or posedge rst) begin 
    if (rst) begin
    sum <= 1'b0; 
    SC <= 1'b0;
    end 
else begin

sum <= hsum2;
SC <= hco1 ^ hco2;

end

end

endmodule

Verilog Files/testingCarrySaveAdder.v
`timescale 1ns / 1ps
//////////////////////////////////////////////////////////////////////////////////
// Company: 
// Engineer: 
// 
// Create Date: 05/11/2025 05:19:37 AM
// Design Name: 
// Module Name: testingCarrySaveAdder
// Project Name: 
// Target Devices: 
// Tool Versions: 
// Description: 
// 
// Dependencies: 
// 
// Revision:
// Revision 0.01 - File Created
// Additional Comments:
// 
//////////////////////////////////////////////////////////////////////////////////


module testingCarrySaveAdder();
reg clk; 
reg x; 
reg y; 
reg rst;
wire sum; 

// Dumpfile for GTKWave
  initial begin
    $dumpfile("testingCarrySaveAdder.vcd");
    $dumpvars(0, testingCarrySaveAdder);
  end

  // Display outputs to the terminal
  initial begin
    $monitor("Time=%0t | rst= %d x=%d y=%d | sum=%d", 
              $time, rst, x, y, sum);
  end

initial begin
 clk<=0;
forever begin
    #10
    clk <= ~clk;
 end
 
 end
 
 
initial begin
rst <= 1;
#5
rst <= 0;
end 

initial begin
    {x,y} = 2'b00;
    #20
    {x,y} = 2'b01;
    #20
    {x,y} = 2'b10;
    #20
    {x,y} = 2'b11;
end
 
carrySave DUT (clk,rst,x,y,sum);
initial begin 
    #100
	$display( "Testing is complete.");
    $finish;
end
endmodule

Verilog Files/testingCarrySaveAdder.vcd
$date
	Sun May 11 07:35:47 2025
$end
$version
	Icarus Verilog
$end
$timescale
	1ps
$end
$scope module testingCarrySaveAdder $end
$var wire 1 ! sum $end
$var reg 1 " clk $end
$var reg 1 # rst $end
$var reg 1 $ x $end
$var reg 1 % y $end
$scope module DUT $end
$var wire 1 & HSUM1 $end
$var wire 1 " clk $end
$var wire 1 ' hco1 $end
$var wire 1 ( hco2 $end
$var wire 1 ) hsum2 $end
$var wire 1 # rst $end
$var wire 1 $ x $end
$var wire 1 % y $end
$var reg 1 * SC $end
$var reg 1 ! sum $end
$upscope $end
$upscope $end
$enddefinitions $end
$comment Show the parameter values. $end
$dumpall
$end
#0
$dumpvars
0*
0)
0(
0'
0&
0%
0$
1#
0"
0!
$end
#5000
0#
#10000
1"
#20000
0"
1)
1&
1%
#30000
1!
1"
#40000
0"
0&
1$
0%
#50000
1"
#60000
0"
0)
1(
1&
1%
#70000
1)
0(
1'
0&
1*
0!
1"
#80000
0"
#90000
1!
1"
